moexr/pandas/__init__.py
moexr/pandas/result.py
moexr_pandas-0.1.0.dist-info/WHEEL
moexr_pandas-0.1.0.dist-info/METADATA
moexr_pandas-0.1.0.dist-info/RECORD
