Metadata-Version: 2.3
Name: moexr-pandas
Version: 0.1.0
Summary: Pandas DataFrames support for moexr tables
Author: Sergey Kostrukov
License: MIT License
Classifier: Development Status :: 4 - Beta
Classifier: Intended Audience :: Developers
Classifier: Intended Audience :: Financial and Insurance Industry
Classifier: License :: OSI Approved :: MIT License
Classifier: Programming Language :: Python :: 3
Classifier: Programming Language :: Python :: 3 :: Only
Classifier: Programming Language :: Python :: 3.11
Classifier: Programming Language :: Python :: 3.12
Classifier: Programming Language :: Python :: 3.13
Classifier: Typing :: Typed
Classifier: Operating System :: OS Independent
Classifier: Topic :: Software Development :: Libraries
Classifier: Topic :: Office/Business :: Financial :: Investment
Requires-Dist: moexr-client>=0.1.0
Requires-Dist: numpy>=1.23.2 ; python_full_version == '3.11.*'
Requires-Dist: numpy>=1.26.0 ; python_full_version >= '3.12'
Requires-Dist: pandas>=2.3,<3
Requires-Python: >=3.11
